hydromt_delft3dfm/__init__.py
hydromt_delft3dfm/dflowfm.py
hydromt_delft3dfm/gis_utils.py
hydromt_delft3dfm/graph_utils.py
hydromt_delft3dfm/mesh_utils.py
hydromt_delft3dfm/utils.py
hydromt_delft3dfm/data/parameters_data.yml
hydromt_delft3dfm/data/branches/channels_defaults.csv
hydromt_delft3dfm/data/branches/pipes_defaults.csv
hydromt_delft3dfm/data/branches/rivers_defaults.csv
hydromt_delft3dfm/data/dflowfm/DFlowFM.mdu
hydromt_delft3dfm/data/landuse/corine_mapping.csv
hydromt_delft3dfm/data/landuse/vito_mapping.csv
hydromt_delft3dfm/data/storages/manholes_defaults.csv
hydromt_delft3dfm/data/structures/bridges_defaults.csv
hydromt_delft3dfm/data/structures/culverts_defaults.csv
hydromt_delft3dfm/workflows/__init__.py
hydromt_delft3dfm/workflows/boundaries.py
hydromt_delft3dfm/workflows/branches.py
hydromt_delft3dfm/workflows/crosssections.py
hydromt_delft3dfm/workflows/dem.py
hydromt_delft3dfm/workflows/manholes.py
hydromt_delft3dfm/workflows/mesh.py
hydromt_delft3dfm/workflows/region.py
hydromt_delft3dfm/workflows/roughness.py
hydromt_delft3dfm/workflows/structures.py
hydromt_delft3dfm-0.3.0.dist-info/entry_points.txt
hydromt_delft3dfm-0.3.0.dist-info/LICENSE
hydromt_delft3dfm-0.3.0.dist-info/WHEEL
hydromt_delft3dfm-0.3.0.dist-info/METADATA
hydromt_delft3dfm-0.3.0.dist-info/RECORD
