Metadata-Version: 2.1
Name: hydromt_delft3dfm
Version: 0.3.0
Summary: hydroMT plugin for Delft3D-FM models.
Author-email: Rinske Hutten <rinske.hutten@deltares.nl>, Xiaohan Li <xiaohan.li@deltares.nl>, Hélène Boisgontier <helene.boisgontier@deltares.nl>, Jelmer Veenstra <jelmer.veenstra@deltares.nl>, Sebastian Hartgring <sebastian.hartgring@deltares.nl>
Requires-Python: >=3.9
Classifier: Development Status :: 2 - Pre-Alpha
Classifier: Intended Audience :: Developers
Classifier: Intended Audience :: Science/Research
Classifier: Topic :: Scientific/Engineering :: Hydrology
Classifier: License :: OSI Approved :: GNU General Public License v3 or later (GPLv3+)
Classifier: Programming Language :: Python :: 3
Classifier: Programming Language :: Python :: 3.9
Classifier: Programming Language :: Python :: 3.10
Classifier: Programming Language :: Python :: 3.11
Classifier: Programming Language :: Python :: 3.12
Requires-Dist: hydromt>=0.10.0, <1
Requires-Dist: geopandas>=0.10, !=1.0.0
Requires-Dist: numpy
Requires-Dist: pandas>=2.0.0
Requires-Dist: xarray
Requires-Dist: hydrolib-core>=0.8.0
Requires-Dist: xugrid>=0.9.0
Requires-Dist: meshkernel>=4.3.0
Requires-Dist: pyproj
Requires-Dist: shapely>=2.0.0
Requires-Dist: scipy
Requires-Dist: pyflwdir>=0.5.4
Requires-Dist: networkx
Requires-Dist: black ; extra == "dev"
Requires-Dist: ruff ; extra == "dev"
Requires-Dist: pre-commit ; extra == "dev"
Requires-Dist: pip>=23.1.2 ; extra == "dev"
Requires-Dist: flit>3.4 ; extra == "dev"
Requires-Dist: twine ; extra == "dev"
Requires-Dist: wheel ; extra == "dev"
Requires-Dist: nbsphinx ; extra == "docs"
Requires-Dist: sphinx ; extra == "docs"
Requires-Dist: sphinx_design ; extra == "docs"
Requires-Dist: pydata-sphinx-theme ; extra == "docs"
Requires-Dist: sphinx_autosummary_accessors ; extra == "docs"
Requires-Dist: jupyterlab ; extra == "examples"
Requires-Dist: notebook ; extra == "examples"
Requires-Dist: cartopy ; extra == "examples"
Requires-Dist: matplotlib ; extra == "examples"
Requires-Dist: pytest>=2.7.3 ; extra == "test"
Requires-Dist: pytest-cov ; extra == "test"
Project-URL: Documentation, http://deltares.github.io/hydromt_delft3dfm/latest/
Project-URL: Source, https://github.com/Deltares/hydromt_delft3dfm
Provides-Extra: dev
Provides-Extra: docs
Provides-Extra: examples
Provides-Extra: test
